blackdoc/__init__.py
blackdoc/__main__.py
blackdoc/autoupdate.py
blackdoc/blackcompat.py
blackdoc/blacken.py
blackdoc/classification.py
blackdoc/colors.py
blackdoc/console.py
blackdoc/diff.py
blackdoc/files.py
blackdoc/report.py
blackdoc/formats/__init__.py
blackdoc/formats/doctest.py
blackdoc/formats/errors.py
blackdoc/formats/ipython.py
blackdoc/formats/markdown.py
blackdoc/formats/none.py
blackdoc/formats/register.py
blackdoc/formats/rst.py
blackdoc/tests/__init__.py
blackdoc/tests/test_autoupdate.py
blackdoc/tests/test_blacken.py
blackdoc/tests/test_classification.py
blackdoc/tests/test_cli.py
blackdoc/tests/test_colors.py
blackdoc/tests/test_doctest.py
blackdoc/tests/test_init.py
blackdoc/tests/test_ipython.py
blackdoc/tests/test_markdown.py
blackdoc/tests/test_none.py
blackdoc/tests/test_report.py
blackdoc/tests/test_rst.py
blackdoc/tests/data/__init__.py
blackdoc/tests/data/__main__.py
blackdoc/tests/data/doctest.py
blackdoc/tests/data/ipython.py
blackdoc/tests/data/rst.py
blackdoc/tests/data/utils.py
blackdoc-0.4.6.dist-info/licenses/LICENSE
blackdoc-0.4.6.dist-info/METADATA
blackdoc-0.4.6.dist-info/WHEEL
blackdoc-0.4.6.dist-info/entry_points.txt
blackdoc-0.4.6.dist-info/top_level.txt
blackdoc-0.4.6.dist-info/RECORD
