Metadata-Version: 2.4
Name: blackdoc
Version: 0.4.6
Summary: run black on documentation code snippets
Author-email: Justus Magin <keewis@posteo.de>
License-Expression: MIT
Project-URL: Repository, https://github.com/keewis/blackdoc
Project-URL: Issues, https://github.com/keewis/blackdoc/issues
Project-URL: Documentation, https://blackdoc.readthedocs.io/en/stable
Classifier: Development Status :: 3 - Alpha
Classifier: Environment :: Console
Classifier: Intended Audience :: Developers
Classifier: Operating System :: OS Independent
Classifier: Programming Language :: Python
Classifier: Programming Language :: Python :: 3.10
Classifier: Programming Language :: Python :: 3.11
Classifier: Programming Language :: Python :: 3.12
Classifier: Programming Language :: Python :: 3.13
Classifier: Programming Language :: Python :: 3 :: Only
Classifier: Topic :: Documentation
Classifier: Topic :: Software Development :: Documentation
Classifier: Topic :: Software Development :: Libraries :: Python Modules
Classifier: Topic :: Software Development :: Quality Assurance
Requires-Python: >=3.10
License-File: LICENSE
Requires-Dist: black>=24.4
Requires-Dist: more-itertools
Requires-Dist: tomli
Requires-Dist: pathspec
Requires-Dist: rich
Dynamic: license-file
